cglbtrial4/__init__.py
cglbtrial4/cli.py
cglbtrial4/conversion.py
cglbtrial4-0.2.0.dist-info/METADATA
cglbtrial4-0.2.0.dist-info/WHEEL
cglbtrial4-0.2.0.dist-info/entry_points.txt
cglbtrial4-0.2.0.dist-info/RECORD
